pathkit/__init__.py
pathkit/base.cp311-win_amd64.pyd
pathkit/base.pyi
pathkit/config.cp311-win_amd64.pyd
pathkit/config.pyi
pathkit/ftp/__init__.py
pathkit/ftp/path.cp311-win_amd64.pyd
pathkit/ftp/path.pyi
pathkit/hdfs/__init__.py
pathkit/hdfs/path.cp311-win_amd64.pyd
pathkit/hdfs/path.pyi
pathkit/local/__init__.py
pathkit/local/path.cp311-win_amd64.pyd
pathkit/local/path.pyi
pathkit/minio/__init__.py
pathkit/minio/path.cp311-win_amd64.pyd
pathkit/minio/path.pyi
pathkit-0.1.3.dist-info/METADATA
pathkit-0.1.3.dist-info/WHEEL
pathkit-0.1.3.dist-info/top_level.txt
pathkit-0.1.3.dist-info/RECORD
