Metadata-Version: 2.2
Name: pathkit
Version: 0.1.3
Summary: Easy way to handle File
Author: Bigollo
Requires-Dist: portalocker
Requires-Dist: cryptography
Dynamic: author
Dynamic: description
Dynamic: description-content-type
Dynamic: requires-dist
Dynamic: summary
